ragconvo/__init__.py
ragconvo-0.0.0.dist-info/METADATA
ragconvo-0.0.0.dist-info/WHEEL
ragconvo-0.0.0.dist-info/RECORD
